LICENSE
MANIFEST.in
README.md
pyproject.toml
setup.py
examples/__init__.py
nemo/__init__.py
nemo/constants.py
nemo/package_info.py
nemo/agents/__init__.py
nemo/agents/voice_agent/__init__.py
nemo/agents/voice_agent/pipecat/__init__.py
nemo/agents/voice_agent/pipecat/frames/__init__.py
nemo/agents/voice_agent/pipecat/frames/frames.py
nemo/agents/voice_agent/pipecat/processors/__init__.py
nemo/agents/voice_agent/pipecat/processors/frameworks/__init__.py
nemo/agents/voice_agent/pipecat/processors/frameworks/rtvi.py
nemo/agents/voice_agent/pipecat/services/__init__.py
nemo/agents/voice_agent/pipecat/services/nemo/__init__.py
nemo/agents/voice_agent/pipecat/services/nemo/diar.py
nemo/agents/voice_agent/pipecat/services/nemo/llm.py
nemo/agents/voice_agent/pipecat/services/nemo/streaming_asr.py
nemo/agents/voice_agent/pipecat/services/nemo/streaming_diar.py
nemo/agents/voice_agent/pipecat/services/nemo/stt.py
nemo/agents/voice_agent/pipecat/services/nemo/tts.py
nemo/agents/voice_agent/pipecat/services/nemo/turn_taking.py
nemo/agents/voice_agent/pipecat/services/nemo/utils.py
nemo/agents/voice_agent/pipecat/transports/__init__.py
nemo/agents/voice_agent/pipecat/transports/base_input.py
nemo/agents/voice_agent/pipecat/transports/base_transport.py
nemo/agents/voice_agent/pipecat/transports/network/__init__.py
nemo/agents/voice_agent/pipecat/transports/network/websocket_server.py
nemo/agents/voice_agent/pipecat/utils/__init__.py
nemo/agents/voice_agent/pipecat/utils/text/__init__.py
nemo/agents/voice_agent/pipecat/utils/text/simple_text_aggregator.py
nemo/agents/voice_agent/utils/__init__.py
nemo/agents/voice_agent/utils/config_manager.py
nemo/collections/__init__.py
nemo/collections/asr/__init__.py
nemo/collections/asr/data/__init__.py
nemo/collections/asr/data/audio_to_ctm_dataset.py
nemo/collections/asr/data/audio_to_diar_label.py
nemo/collections/asr/data/audio_to_diar_label_lhotse.py
nemo/collections/asr/data/audio_to_label.py
nemo_toolkit_asr.egg-info/PKG-INFO
nemo_toolkit_asr.egg-info/SOURCES.txt
nemo_toolkit_asr.egg-info/dependency_links.txt
nemo_toolkit_asr.egg-info/entry_points.txt
nemo_toolkit_asr.egg-info/not-zip-safe
nemo_toolkit_asr.egg-info/requires.txt
nemo_toolkit_asr.egg-info/top_level.txt
