Metadata-Version: 2.4
Name: nemo-toolkit-asr
Version: 2.7.0rc4
Summary: NeMo - a toolkit for Conversational AI
Home-page: https://github.com/nvidia/nemo
Download-URL: https://github.com/NVIDIA/NeMo/releases
Author: NVIDIA
Author-email: NVIDIA <nemo-toolkit@nvidia.com>
Maintainer: NVIDIA
Maintainer-email: NVIDIA <nemo-toolkit@nvidia.com>
License:                                  Apache License
Project-URL: Download, https://github.com/NVIDIA/NeMo/releases
Project-URL: Homepage, https://github.com/nvidia/nemo
Keywords: NLP,NeMo,deep,gpu,language,learning,learning,machine,nvidia,pytorch,speech,torch,tts
Classifier: Development Status :: 5 - Production/Stable
Classifier: Environment :: Console
Classifier: Intended Audience :: Developers
Classifier: Intended Audience :: Information Technology
Classifier: Intended Audience :: Science/Research
Classifier: License :: OSI Approved :: Apache Software License
Classifier: Natural Language :: English
Classifier: Operating System :: OS Independent
Classifier: Programming Language :: Python :: 3
Classifier: Programming Language :: Python :: 3.10
Classifier: Topic :: Scientific/Engineering :: Artificial Intelligence
Classifier: Topic :: Scientific/Engineering :: Image Recognition
Classifier: Topic :: Scientific/Engineering :: Mathematics
Classifier: Topic :: Scientific/Engineering
Classifier: Topic :: Software Development :: Libraries :: Python Modules
Classifier: Topic :: Software Development :: Libraries
Classifier: Topic :: Utilities
Requires-Python: >=3.10
License-File: LICENSE
Requires-Dist: fsspec==2024.12.0
Requires-Dist: huggingface_hub>=0.24
Requires-Dist: numba; platform_system == "Darwin"
Requires-Dist: numba-cuda==0.15.1; platform_system != "Darwin"
Requires-Dist: cuda-bindings; platform_system != "Darwin"
Requires-Dist: numexpr<2.14.0
Requires-Dist: numpy>=1.22
Requires-Dist: onnx>=1.7.0
Requires-Dist: protobuf~=5.29.5
Requires-Dist: python-dateutil
Requires-Dist: ruamel.yaml
Requires-Dist: scikit-learn
Requires-Dist: setuptools>=70.0.0
Requires-Dist: tensorboard
Requires-Dist: text-unidecode
Requires-Dist: torch
Requires-Dist: tqdm>=4.41.0
Requires-Dist: wget
Requires-Dist: wrapt
Provides-Extra: test
Requires-Dist: black~=24.3; extra == "test"
Requires-Dist: click>=8.1; extra == "test"
Requires-Dist: coverage; extra == "test"
Requires-Dist: isort<6.0.0,>5.1.0; extra == "test"
Requires-Dist: parameterized; extra == "test"
Requires-Dist: pytest; extra == "test"
Requires-Dist: pytest-httpserver; extra == "test"
Requires-Dist: pytest-mock; extra == "test"
Requires-Dist: pytest-runner; extra == "test"
Requires-Dist: ruamel.yaml; extra == "test"
Requires-Dist: sphinx; extra == "test"
Requires-Dist: sphinxcontrib-bibtex; extra == "test"
Requires-Dist: wandb; extra == "test"
Requires-Dist: wget; extra == "test"
Requires-Dist: wrapt; extra == "test"
Requires-Dist: attrdict; extra == "test"
Requires-Dist: cdifflib==1.2.6; extra == "test"
Requires-Dist: einops; extra == "test"
Requires-Dist: janome; extra == "test"
Requires-Dist: jieba; extra == "test"
Requires-Dist: kornia; extra == "test"
Requires-Dist: librosa; extra == "test"
Requires-Dist: matplotlib; extra == "test"
Requires-Dist: nemo_text_processing; ("arm" not in platform_machine and "aarch" not in platform_machine and sys_platform != "darwin") and extra == "test"
Requires-Dist: nltk; extra == "test"
Requires-Dist: pandas; extra == "test"
Requires-Dist: pypinyin; extra == "test"
Requires-Dist: pypinyin-dict; extra == "test"
Requires-Dist: seaborn; extra == "test"
Requires-Dist: pyopenjtalk; extra == "test"
Requires-Dist: datasets; extra == "test"
Requires-Dist: einops; extra == "test"
Requires-Dist: inflect; extra == "test"
Requires-Dist: mediapy==1.1.6; extra == "test"
Requires-Dist: pandas; extra == "test"
Requires-Dist: sacremoses>=0.0.43; extra == "test"
Requires-Dist: sentencepiece<1.0.0; extra == "test"
Requires-Dist: cloudpickle; extra == "test"
Requires-Dist: fiddle; extra == "test"
Requires-Dist: hydra-core<=1.3.2,>1.3; extra == "test"
Requires-Dist: lightning<=2.4.0,>2.2.1; extra == "test"
Requires-Dist: omegaconf<=2.3; extra == "test"
Requires-Dist: peft; extra == "test"
Requires-Dist: torchmetrics>=0.11.0; extra == "test"
Requires-Dist: transformers; extra == "test"
Requires-Dist: wandb; extra == "test"
Requires-Dist: webdataset>=0.2.86; extra == "test"
Requires-Dist: nv_one_logger_core>=2.3.1; extra == "test"
Requires-Dist: nv_one_logger_training_telemetry>=2.3.1; extra == "test"
Requires-Dist: nv_one_logger_pytorch_lightning_integration>=2.3.1; extra == "test"
Provides-Extra: run
Requires-Dist: nemo_run; extra == "run"
Provides-Extra: core
Requires-Dist: cloudpickle; extra == "core"
Requires-Dist: fiddle; extra == "core"
Requires-Dist: hydra-core<=1.3.2,>1.3; extra == "core"
Requires-Dist: lightning<=2.4.0,>2.2.1; extra == "core"
Requires-Dist: omegaconf<=2.3; extra == "core"
Requires-Dist: peft; extra == "core"
Requires-Dist: torchmetrics>=0.11.0; extra == "core"
Requires-Dist: transformers; extra == "core"
Requires-Dist: wandb; extra == "core"
Requires-Dist: webdataset>=0.2.86; extra == "core"
Requires-Dist: nv_one_logger_core>=2.3.1; extra == "core"
Requires-Dist: nv_one_logger_training_telemetry>=2.3.1; extra == "core"
Requires-Dist: nv_one_logger_pytorch_lightning_integration>=2.3.1; extra == "core"
Provides-Extra: lightning
Requires-Dist: cloudpickle; extra == "lightning"
Requires-Dist: fiddle; extra == "lightning"
Requires-Dist: hydra-core<=1.3.2,>1.3; extra == "lightning"
Requires-Dist: lightning<=2.4.0,>2.2.1; extra == "lightning"
Requires-Dist: omegaconf<=2.3; extra == "lightning"
Requires-Dist: peft; extra == "lightning"
Requires-Dist: torchmetrics>=0.11.0; extra == "lightning"
Requires-Dist: transformers; extra == "lightning"
Requires-Dist: wandb; extra == "lightning"
Requires-Dist: webdataset>=0.2.86; extra == "lightning"
Requires-Dist: nv_one_logger_core>=2.3.1; extra == "lightning"
Requires-Dist: nv_one_logger_training_telemetry>=2.3.1; extra == "lightning"
Requires-Dist: nv_one_logger_pytorch_lightning_integration>=2.3.1; extra == "lightning"
Provides-Extra: common-only
Requires-Dist: datasets; extra == "common-only"
Requires-Dist: einops; extra == "common-only"
Requires-Dist: inflect; extra == "common-only"
Requires-Dist: mediapy==1.1.6; extra == "common-only"
Requires-Dist: pandas; extra == "common-only"
Requires-Dist: sacremoses>=0.0.43; extra == "common-only"
Requires-Dist: sentencepiece<1.0.0; extra == "common-only"
Provides-Extra: asr-only
Requires-Dist: braceexpand; extra == "asr-only"
Requires-Dist: diskcache; extra == "asr-only"
Requires-Dist: editdistance; extra == "asr-only"
Requires-Dist: einops; extra == "asr-only"
Requires-Dist: jiwer<4.0.0,>=3.1.0; extra == "asr-only"
Requires-Dist: kaldi-python-io; extra == "asr-only"
Requires-Dist: kaldialign==0.9.2; extra == "asr-only"
Requires-Dist: lhotse>=1.32.0; extra == "asr-only"
Requires-Dist: librosa>=0.10.1; extra == "asr-only"
Requires-Dist: marshmallow; extra == "asr-only"
Requires-Dist: optuna; extra == "asr-only"
Requires-Dist: packaging; extra == "asr-only"
Requires-Dist: pyannote.core; extra == "asr-only"
Requires-Dist: pyannote.metrics; extra == "asr-only"
Requires-Dist: pydub; extra == "asr-only"
Requires-Dist: pyloudnorm; extra == "asr-only"
Requires-Dist: resampy; extra == "asr-only"
Requires-Dist: ruamel.yaml; extra == "asr-only"
Requires-Dist: scipy>=0.14; extra == "asr-only"
Requires-Dist: soundfile; extra == "asr-only"
Requires-Dist: sox<=1.5.0; extra == "asr-only"
Requires-Dist: whisper_normalizer; extra == "asr-only"
Provides-Extra: nlp-only
Requires-Dist: accelerated-scan; extra == "nlp-only"
Requires-Dist: boto3; extra == "nlp-only"
Requires-Dist: faiss-cpu; extra == "nlp-only"
Requires-Dist: flask_restful; extra == "nlp-only"
Requires-Dist: ftfy; extra == "nlp-only"
Requires-Dist: gdown; extra == "nlp-only"
Requires-Dist: h5py; extra == "nlp-only"
Requires-Dist: ijson; extra == "nlp-only"
Requires-Dist: jieba; extra == "nlp-only"
Requires-Dist: markdown2; extra == "nlp-only"
Requires-Dist: matplotlib>=3.3.2; extra == "nlp-only"
Requires-Dist: megatron_core; extra == "nlp-only"
Requires-Dist: multi-storage-client>=0.21.0; extra == "nlp-only"
Requires-Dist: nltk>=3.6.5; extra == "nlp-only"
Requires-Dist: numpy<2; extra == "nlp-only"
Requires-Dist: nvidia-modelopt==0.37.0; extra == "nlp-only"
Requires-Dist: nvidia-resiliency-ext<1.0.0,>=0.3.0; platform_system != "Darwin" and extra == "nlp-only"
Requires-Dist: nvtx; extra == "nlp-only"
Requires-Dist: opencc; extra == "nlp-only"
Requires-Dist: pangu; extra == "nlp-only"
Requires-Dist: prettytable; extra == "nlp-only"
Requires-Dist: rapidfuzz; extra == "nlp-only"
Requires-Dist: rouge_score; extra == "nlp-only"
Requires-Dist: sacrebleu; extra == "nlp-only"
Requires-Dist: sentence_transformers; extra == "nlp-only"
Requires-Dist: tensorstore<0.1.72; platform_system != "Darwin" and extra == "nlp-only"
Requires-Dist: tiktoken==0.7.0; extra == "nlp-only"
Requires-Dist: zarr<3.0.0,>=2.18.2; extra == "nlp-only"
Provides-Extra: tts
Requires-Dist: attrdict; extra == "tts"
Requires-Dist: cdifflib==1.2.6; extra == "tts"
Requires-Dist: einops; extra == "tts"
Requires-Dist: janome; extra == "tts"
Requires-Dist: jieba; extra == "tts"
Requires-Dist: kornia; extra == "tts"
Requires-Dist: librosa; extra == "tts"
Requires-Dist: matplotlib; extra == "tts"
Requires-Dist: nemo_text_processing; ("arm" not in platform_machine and "aarch" not in platform_machine and sys_platform != "darwin") and extra == "tts"
Requires-Dist: nltk; extra == "tts"
Requires-Dist: pandas; extra == "tts"
Requires-Dist: pypinyin; extra == "tts"
Requires-Dist: pypinyin-dict; extra == "tts"
Requires-Dist: seaborn; extra == "tts"
Requires-Dist: pyopenjtalk; extra == "tts"
Requires-Dist: braceexpand; extra == "tts"
Requires-Dist: diskcache; extra == "tts"
Requires-Dist: editdistance; extra == "tts"
Requires-Dist: einops; extra == "tts"
Requires-Dist: jiwer<4.0.0,>=3.1.0; extra == "tts"
Requires-Dist: kaldi-python-io; extra == "tts"
Requires-Dist: kaldialign==0.9.2; extra == "tts"
Requires-Dist: lhotse>=1.32.0; extra == "tts"
Requires-Dist: librosa>=0.10.1; extra == "tts"
Requires-Dist: marshmallow; extra == "tts"
Requires-Dist: optuna; extra == "tts"
Requires-Dist: packaging; extra == "tts"
Requires-Dist: pyannote.core; extra == "tts"
Requires-Dist: pyannote.metrics; extra == "tts"
Requires-Dist: pydub; extra == "tts"
Requires-Dist: pyloudnorm; extra == "tts"
Requires-Dist: resampy; extra == "tts"
Requires-Dist: ruamel.yaml; extra == "tts"
Requires-Dist: scipy>=0.14; extra == "tts"
Requires-Dist: soundfile; extra == "tts"
Requires-Dist: sox<=1.5.0; extra == "tts"
Requires-Dist: whisper_normalizer; extra == "tts"
Requires-Dist: datasets; extra == "tts"
Requires-Dist: einops; extra == "tts"
Requires-Dist: inflect; extra == "tts"
Requires-Dist: mediapy==1.1.6; extra == "tts"
Requires-Dist: pandas; extra == "tts"
Requires-Dist: sacremoses>=0.0.43; extra == "tts"
Requires-Dist: sentencepiece<1.0.0; extra == "tts"
Requires-Dist: cloudpickle; extra == "tts"
Requires-Dist: fiddle; extra == "tts"
Requires-Dist: hydra-core<=1.3.2,>1.3; extra == "tts"
Requires-Dist: lightning<=2.4.0,>2.2.1; extra == "tts"
Requires-Dist: omegaconf<=2.3; extra == "tts"
Requires-Dist: peft; extra == "tts"
Requires-Dist: torchmetrics>=0.11.0; extra == "tts"
Requires-Dist: transformers; extra == "tts"
Requires-Dist: wandb; extra == "tts"
Requires-Dist: webdataset>=0.2.86; extra == "tts"
Requires-Dist: nv_one_logger_core>=2.3.1; extra == "tts"
Requires-Dist: nv_one_logger_training_telemetry>=2.3.1; extra == "tts"
Requires-Dist: nv_one_logger_pytorch_lightning_integration>=2.3.1; extra == "tts"
Requires-Dist: datasets; extra == "tts"
Requires-Dist: einops; extra == "tts"
Requires-Dist: inflect; extra == "tts"
Requires-Dist: mediapy==1.1.6; extra == "tts"
Requires-Dist: pandas; extra == "tts"
Requires-Dist: sacremoses>=0.0.43; extra == "tts"
Requires-Dist: sentencepiece<1.0.0; extra == "tts"
Requires-Dist: cloudpickle; extra == "tts"
Requires-Dist: fiddle; extra == "tts"
Requires-Dist: hydra-core<=1.3.2,>1.3; extra == "tts"
Requires-Dist: lightning<=2.4.0,>2.2.1; extra == "tts"
Requires-Dist: omegaconf<=2.3; extra == "tts"
Requires-Dist: peft; extra == "tts"
Requires-Dist: torchmetrics>=0.11.0; extra == "tts"
Requires-Dist: transformers; extra == "tts"
Requires-Dist: wandb; extra == "tts"
Requires-Dist: webdataset>=0.2.86; extra == "tts"
Requires-Dist: nv_one_logger_core>=2.3.1; extra == "tts"
Requires-Dist: nv_one_logger_training_telemetry>=2.3.1; extra == "tts"
Requires-Dist: nv_one_logger_pytorch_lightning_integration>=2.3.1; extra == "tts"
Provides-Extra: slu
Requires-Dist: jiwer<4.0.0,>=2.0.0; extra == "slu"
Requires-Dist: progress>=1.5; extra == "slu"
Requires-Dist: tabulate>=0.8.7; extra == "slu"
Requires-Dist: textdistance>=4.1.5; extra == "slu"
Requires-Dist: tqdm; extra == "slu"
Requires-Dist: braceexpand; extra == "slu"
Requires-Dist: diskcache; extra == "slu"
Requires-Dist: editdistance; extra == "slu"
Requires-Dist: einops; extra == "slu"
Requires-Dist: jiwer<4.0.0,>=3.1.0; extra == "slu"
Requires-Dist: kaldi-python-io; extra == "slu"
Requires-Dist: kaldialign==0.9.2; extra == "slu"
Requires-Dist: lhotse>=1.32.0; extra == "slu"
Requires-Dist: librosa>=0.10.1; extra == "slu"
Requires-Dist: marshmallow; extra == "slu"
Requires-Dist: optuna; extra == "slu"
Requires-Dist: packaging; extra == "slu"
Requires-Dist: pyannote.core; extra == "slu"
Requires-Dist: pyannote.metrics; extra == "slu"
Requires-Dist: pydub; extra == "slu"
Requires-Dist: pyloudnorm; extra == "slu"
Requires-Dist: resampy; extra == "slu"
Requires-Dist: ruamel.yaml; extra == "slu"
Requires-Dist: scipy>=0.14; extra == "slu"
Requires-Dist: soundfile; extra == "slu"
Requires-Dist: sox<=1.5.0; extra == "slu"
Requires-Dist: whisper_normalizer; extra == "slu"
Requires-Dist: datasets; extra == "slu"
Requires-Dist: einops; extra == "slu"
Requires-Dist: inflect; extra == "slu"
Requires-Dist: mediapy==1.1.6; extra == "slu"
Requires-Dist: pandas; extra == "slu"
Requires-Dist: sacremoses>=0.0.43; extra == "slu"
Requires-Dist: sentencepiece<1.0.0; extra == "slu"
Requires-Dist: cloudpickle; extra == "slu"
Requires-Dist: fiddle; extra == "slu"
Requires-Dist: hydra-core<=1.3.2,>1.3; extra == "slu"
Requires-Dist: lightning<=2.4.0,>2.2.1; extra == "slu"
Requires-Dist: omegaconf<=2.3; extra == "slu"
Requires-Dist: peft; extra == "slu"
Requires-Dist: torchmetrics>=0.11.0; extra == "slu"
Requires-Dist: transformers; extra == "slu"
Requires-Dist: wandb; extra == "slu"
Requires-Dist: webdataset>=0.2.86; extra == "slu"
Requires-Dist: nv_one_logger_core>=2.3.1; extra == "slu"
Requires-Dist: nv_one_logger_training_telemetry>=2.3.1; extra == "slu"
Requires-Dist: nv_one_logger_pytorch_lightning_integration>=2.3.1; extra == "slu"
Provides-Extra: multimodal-only
Requires-Dist: addict; extra == "multimodal-only"
Requires-Dist: clip; extra == "multimodal-only"
Requires-Dist: decord; (sys_platform == "linux" and platform_machine == "x86_64") and extra == "multimodal-only"
Requires-Dist: diffusers>=0.19.3; extra == "multimodal-only"
Requires-Dist: einops_exts; extra == "multimodal-only"
Requires-Dist: imageio; extra == "multimodal-only"
Requires-Dist: kornia; extra == "multimodal-only"
Requires-Dist: megatron-energon==5.2.0; extra == "multimodal-only"
Requires-Dist: nerfacc>=0.5.3; extra == "multimodal-only"
Requires-Dist: open_clip_torch==2.24.0; extra == "multimodal-only"
Requires-Dist: qwen_vl_utils; extra == "multimodal-only"
Requires-Dist: taming-transformers; extra == "multimodal-only"
Requires-Dist: torchdiffeq; extra == "multimodal-only"
Requires-Dist: torchsde; extra == "multimodal-only"
Requires-Dist: trimesh; extra == "multimodal-only"
Provides-Extra: audio
Requires-Dist: einops; extra == "audio"
Requires-Dist: lhotse>=1.31.1; extra == "audio"
Requires-Dist: librosa>=0.10.0; extra == "audio"
Requires-Dist: matplotlib; extra == "audio"
Requires-Dist: pesq; (platform_machine != "x86_64" or platform_system != "Darwin") and extra == "audio"
Requires-Dist: pystoi; extra == "audio"
Requires-Dist: scipy>=0.14; extra == "audio"
Requires-Dist: soundfile; extra == "audio"
Requires-Dist: datasets; extra == "audio"
Requires-Dist: einops; extra == "audio"
Requires-Dist: inflect; extra == "audio"
Requires-Dist: mediapy==1.1.6; extra == "audio"
Requires-Dist: pandas; extra == "audio"
Requires-Dist: sacremoses>=0.0.43; extra == "audio"
Requires-Dist: sentencepiece<1.0.0; extra == "audio"
Requires-Dist: cloudpickle; extra == "audio"
Requires-Dist: fiddle; extra == "audio"
Requires-Dist: hydra-core<=1.3.2,>1.3; extra == "audio"
Requires-Dist: lightning<=2.4.0,>2.2.1; extra == "audio"
Requires-Dist: omegaconf<=2.3; extra == "audio"
Requires-Dist: peft; extra == "audio"
Requires-Dist: torchmetrics>=0.11.0; extra == "audio"
Requires-Dist: transformers; extra == "audio"
Requires-Dist: wandb; extra == "audio"
Requires-Dist: webdataset>=0.2.86; extra == "audio"
Requires-Dist: nv_one_logger_core>=2.3.1; extra == "audio"
Requires-Dist: nv_one_logger_training_telemetry>=2.3.1; extra == "audio"
Requires-Dist: nv_one_logger_pytorch_lightning_integration>=2.3.1; extra == "audio"
Provides-Extra: all
Requires-Dist: black~=24.3; extra == "all"
Requires-Dist: click>=8.1; extra == "all"
Requires-Dist: coverage; extra == "all"
Requires-Dist: isort<6.0.0,>5.1.0; extra == "all"
Requires-Dist: parameterized; extra == "all"
Requires-Dist: pytest; extra == "all"
Requires-Dist: pytest-httpserver; extra == "all"
Requires-Dist: pytest-mock; extra == "all"
Requires-Dist: pytest-runner; extra == "all"
Requires-Dist: ruamel.yaml; extra == "all"
Requires-Dist: sphinx; extra == "all"
Requires-Dist: sphinxcontrib-bibtex; extra == "all"
Requires-Dist: wandb; extra == "all"
Requires-Dist: wget; extra == "all"
Requires-Dist: wrapt; extra == "all"
Requires-Dist: nemo_run; extra == "all"
Requires-Dist: cloudpickle; extra == "all"
Requires-Dist: fiddle; extra == "all"
Requires-Dist: hydra-core<=1.3.2,>1.3; extra == "all"
Requires-Dist: lightning<=2.4.0,>2.2.1; extra == "all"
Requires-Dist: omegaconf<=2.3; extra == "all"
Requires-Dist: peft; extra == "all"
Requires-Dist: torchmetrics>=0.11.0; extra == "all"
Requires-Dist: transformers; extra == "all"
Requires-Dist: wandb; extra == "all"
Requires-Dist: webdataset>=0.2.86; extra == "all"
Requires-Dist: nv_one_logger_core>=2.3.1; extra == "all"
Requires-Dist: nv_one_logger_training_telemetry>=2.3.1; extra == "all"
Requires-Dist: nv_one_logger_pytorch_lightning_integration>=2.3.1; extra == "all"
Requires-Dist: cloudpickle; extra == "all"
Requires-Dist: fiddle; extra == "all"
Requires-Dist: hydra-core<=1.3.2,>1.3; extra == "all"
Requires-Dist: lightning<=2.4.0,>2.2.1; extra == "all"
Requires-Dist: omegaconf<=2.3; extra == "all"
Requires-Dist: peft; extra == "all"
Requires-Dist: torchmetrics>=0.11.0; extra == "all"
Requires-Dist: transformers; extra == "all"
Requires-Dist: wandb; extra == "all"
Requires-Dist: webdataset>=0.2.86; extra == "all"
Requires-Dist: nv_one_logger_core>=2.3.1; extra == "all"
Requires-Dist: nv_one_logger_training_telemetry>=2.3.1; extra == "all"
Requires-Dist: nv_one_logger_pytorch_lightning_integration>=2.3.1; extra == "all"
Requires-Dist: datasets; extra == "all"
Requires-Dist: einops; extra == "all"
Requires-Dist: inflect; extra == "all"
Requires-Dist: mediapy==1.1.6; extra == "all"
Requires-Dist: pandas; extra == "all"
Requires-Dist: sacremoses>=0.0.43; extra == "all"
Requires-Dist: sentencepiece<1.0.0; extra == "all"
Requires-Dist: braceexpand; extra == "all"
Requires-Dist: diskcache; extra == "all"
Requires-Dist: editdistance; extra == "all"
Requires-Dist: einops; extra == "all"
Requires-Dist: jiwer<4.0.0,>=3.1.0; extra == "all"
Requires-Dist: kaldi-python-io; extra == "all"
Requires-Dist: kaldialign==0.9.2; extra == "all"
Requires-Dist: lhotse>=1.32.0; extra == "all"
Requires-Dist: librosa>=0.10.1; extra == "all"
Requires-Dist: marshmallow; extra == "all"
Requires-Dist: optuna; extra == "all"
Requires-Dist: packaging; extra == "all"
Requires-Dist: pyannote.core; extra == "all"
Requires-Dist: pyannote.metrics; extra == "all"
Requires-Dist: pydub; extra == "all"
Requires-Dist: pyloudnorm; extra == "all"
Requires-Dist: resampy; extra == "all"
Requires-Dist: ruamel.yaml; extra == "all"
Requires-Dist: scipy>=0.14; extra == "all"
Requires-Dist: soundfile; extra == "all"
Requires-Dist: sox<=1.5.0; extra == "all"
Requires-Dist: whisper_normalizer; extra == "all"
Requires-Dist: accelerated-scan; extra == "all"
Requires-Dist: boto3; extra == "all"
Requires-Dist: faiss-cpu; extra == "all"
Requires-Dist: flask_restful; extra == "all"
Requires-Dist: ftfy; extra == "all"
Requires-Dist: gdown; extra == "all"
Requires-Dist: h5py; extra == "all"
Requires-Dist: ijson; extra == "all"
Requires-Dist: jieba; extra == "all"
Requires-Dist: markdown2; extra == "all"
Requires-Dist: matplotlib>=3.3.2; extra == "all"
Requires-Dist: megatron_core; extra == "all"
Requires-Dist: multi-storage-client>=0.21.0; extra == "all"
Requires-Dist: nltk>=3.6.5; extra == "all"
Requires-Dist: numpy<2; extra == "all"
Requires-Dist: nvidia-modelopt==0.37.0; extra == "all"
Requires-Dist: nvidia-resiliency-ext<1.0.0,>=0.3.0; platform_system != "Darwin" and extra == "all"
Requires-Dist: nvtx; extra == "all"
Requires-Dist: opencc; extra == "all"
Requires-Dist: pangu; extra == "all"
Requires-Dist: prettytable; extra == "all"
Requires-Dist: rapidfuzz; extra == "all"
Requires-Dist: rouge_score; extra == "all"
Requires-Dist: sacrebleu; extra == "all"
Requires-Dist: sentence_transformers; extra == "all"
Requires-Dist: tensorstore<0.1.72; platform_system != "Darwin" and extra == "all"
Requires-Dist: tiktoken==0.7.0; extra == "all"
Requires-Dist: zarr<3.0.0,>=2.18.2; extra == "all"
Requires-Dist: attrdict; extra == "all"
Requires-Dist: cdifflib==1.2.6; extra == "all"
Requires-Dist: einops; extra == "all"
Requires-Dist: janome; extra == "all"
Requires-Dist: jieba; extra == "all"
Requires-Dist: kornia; extra == "all"
Requires-Dist: librosa; extra == "all"
Requires-Dist: matplotlib; extra == "all"
Requires-Dist: nemo_text_processing; ("arm" not in platform_machine and "aarch" not in platform_machine and sys_platform != "darwin") and extra == "all"
Requires-Dist: nltk; extra == "all"
Requires-Dist: pandas; extra == "all"
Requires-Dist: pypinyin; extra == "all"
Requires-Dist: pypinyin-dict; extra == "all"
Requires-Dist: seaborn; extra == "all"
Requires-Dist: pyopenjtalk; extra == "all"
Requires-Dist: jiwer<4.0.0,>=2.0.0; extra == "all"
Requires-Dist: progress>=1.5; extra == "all"
Requires-Dist: tabulate>=0.8.7; extra == "all"
Requires-Dist: textdistance>=4.1.5; extra == "all"
Requires-Dist: tqdm; extra == "all"
Requires-Dist: addict; extra == "all"
Requires-Dist: clip; extra == "all"
Requires-Dist: decord; (sys_platform == "linux" and platform_machine == "x86_64") and extra == "all"
Requires-Dist: diffusers>=0.19.3; extra == "all"
Requires-Dist: einops_exts; extra == "all"
Requires-Dist: imageio; extra == "all"
Requires-Dist: kornia; extra == "all"
Requires-Dist: megatron-energon==5.2.0; extra == "all"
Requires-Dist: nerfacc>=0.5.3; extra == "all"
Requires-Dist: open_clip_torch==2.24.0; extra == "all"
Requires-Dist: qwen_vl_utils; extra == "all"
Requires-Dist: taming-transformers; extra == "all"
Requires-Dist: torchdiffeq; extra == "all"
Requires-Dist: torchsde; extra == "all"
Requires-Dist: trimesh; extra == "all"
Requires-Dist: einops; extra == "all"
Requires-Dist: lhotse>=1.31.1; extra == "all"
Requires-Dist: librosa>=0.10.0; extra == "all"
Requires-Dist: matplotlib; extra == "all"
Requires-Dist: pesq; (platform_machine != "x86_64" or platform_system != "Darwin") and extra == "all"
Requires-Dist: pystoi; extra == "all"
Requires-Dist: scipy>=0.14; extra == "all"
Requires-Dist: soundfile; extra == "all"
Provides-Extra: common
Requires-Dist: datasets; extra == "common"
Requires-Dist: einops; extra == "common"
Requires-Dist: inflect; extra == "common"
Requires-Dist: mediapy==1.1.6; extra == "common"
Requires-Dist: pandas; extra == "common"
Requires-Dist: sacremoses>=0.0.43; extra == "common"
Requires-Dist: sentencepiece<1.0.0; extra == "common"
Requires-Dist: cloudpickle; extra == "common"
Requires-Dist: fiddle; extra == "common"
Requires-Dist: hydra-core<=1.3.2,>1.3; extra == "common"
Requires-Dist: lightning<=2.4.0,>2.2.1; extra == "common"
Requires-Dist: omegaconf<=2.3; extra == "common"
Requires-Dist: peft; extra == "common"
Requires-Dist: torchmetrics>=0.11.0; extra == "common"
Requires-Dist: transformers; extra == "common"
Requires-Dist: wandb; extra == "common"
Requires-Dist: webdataset>=0.2.86; extra == "common"
Requires-Dist: nv_one_logger_core>=2.3.1; extra == "common"
Requires-Dist: nv_one_logger_training_telemetry>=2.3.1; extra == "common"
Requires-Dist: nv_one_logger_pytorch_lightning_integration>=2.3.1; extra == "common"
Provides-Extra: asr
Requires-Dist: braceexpand; extra == "asr"
Requires-Dist: diskcache; extra == "asr"
Requires-Dist: editdistance; extra == "asr"
Requires-Dist: einops; extra == "asr"
Requires-Dist: jiwer<4.0.0,>=3.1.0; extra == "asr"
Requires-Dist: kaldi-python-io; extra == "asr"
Requires-Dist: kaldialign==0.9.2; extra == "asr"
Requires-Dist: lhotse>=1.32.0; extra == "asr"
Requires-Dist: librosa>=0.10.1; extra == "asr"
Requires-Dist: marshmallow; extra == "asr"
Requires-Dist: optuna; extra == "asr"
Requires-Dist: packaging; extra == "asr"
Requires-Dist: pyannote.core; extra == "asr"
Requires-Dist: pyannote.metrics; extra == "asr"
Requires-Dist: pydub; extra == "asr"
Requires-Dist: pyloudnorm; extra == "asr"
Requires-Dist: resampy; extra == "asr"
Requires-Dist: ruamel.yaml; extra == "asr"
Requires-Dist: scipy>=0.14; extra == "asr"
Requires-Dist: soundfile; extra == "asr"
Requires-Dist: sox<=1.5.0; extra == "asr"
Requires-Dist: whisper_normalizer; extra == "asr"
Requires-Dist: datasets; extra == "asr"
Requires-Dist: einops; extra == "asr"
Requires-Dist: inflect; extra == "asr"
Requires-Dist: mediapy==1.1.6; extra == "asr"
Requires-Dist: pandas; extra == "asr"
Requires-Dist: sacremoses>=0.0.43; extra == "asr"
Requires-Dist: sentencepiece<1.0.0; extra == "asr"
Requires-Dist: cloudpickle; extra == "asr"
Requires-Dist: fiddle; extra == "asr"
Requires-Dist: hydra-core<=1.3.2,>1.3; extra == "asr"
Requires-Dist: lightning<=2.4.0,>2.2.1; extra == "asr"
Requires-Dist: omegaconf<=2.3; extra == "asr"
Requires-Dist: peft; extra == "asr"
Requires-Dist: torchmetrics>=0.11.0; extra == "asr"
Requires-Dist: transformers; extra == "asr"
Requires-Dist: wandb; extra == "asr"
Requires-Dist: webdataset>=0.2.86; extra == "asr"
Requires-Dist: nv_one_logger_core>=2.3.1; extra == "asr"
Requires-Dist: nv_one_logger_training_telemetry>=2.3.1; extra == "asr"
Requires-Dist: nv_one_logger_pytorch_lightning_integration>=2.3.1; extra == "asr"
Provides-Extra: nlp
Requires-Dist: accelerated-scan; extra == "nlp"
Requires-Dist: boto3; extra == "nlp"
Requires-Dist: faiss-cpu; extra == "nlp"
Requires-Dist: flask_restful; extra == "nlp"
Requires-Dist: ftfy; extra == "nlp"
Requires-Dist: gdown; extra == "nlp"
Requires-Dist: h5py; extra == "nlp"
Requires-Dist: ijson; extra == "nlp"
Requires-Dist: jieba; extra == "nlp"
Requires-Dist: markdown2; extra == "nlp"
Requires-Dist: matplotlib>=3.3.2; extra == "nlp"
Requires-Dist: megatron_core; extra == "nlp"
Requires-Dist: multi-storage-client>=0.21.0; extra == "nlp"
Requires-Dist: nltk>=3.6.5; extra == "nlp"
Requires-Dist: numpy<2; extra == "nlp"
Requires-Dist: nvidia-modelopt==0.37.0; extra == "nlp"
Requires-Dist: nvidia-resiliency-ext<1.0.0,>=0.3.0; platform_system != "Darwin" and extra == "nlp"
Requires-Dist: nvtx; extra == "nlp"
Requires-Dist: opencc; extra == "nlp"
Requires-Dist: pangu; extra == "nlp"
Requires-Dist: prettytable; extra == "nlp"
Requires-Dist: rapidfuzz; extra == "nlp"
Requires-Dist: rouge_score; extra == "nlp"
Requires-Dist: sacrebleu; extra == "nlp"
Requires-Dist: sentence_transformers; extra == "nlp"
Requires-Dist: tensorstore<0.1.72; platform_system != "Darwin" and extra == "nlp"
Requires-Dist: tiktoken==0.7.0; extra == "nlp"
Requires-Dist: zarr<3.0.0,>=2.18.2; extra == "nlp"
Requires-Dist: datasets; extra == "nlp"
Requires-Dist: einops; extra == "nlp"
Requires-Dist: inflect; extra == "nlp"
Requires-Dist: mediapy==1.1.6; extra == "nlp"
Requires-Dist: pandas; extra == "nlp"
Requires-Dist: sacremoses>=0.0.43; extra == "nlp"
Requires-Dist: sentencepiece<1.0.0; extra == "nlp"
Requires-Dist: cloudpickle; extra == "nlp"
Requires-Dist: fiddle; extra == "nlp"
Requires-Dist: hydra-core<=1.3.2,>1.3; extra == "nlp"
Requires-Dist: lightning<=2.4.0,>2.2.1; extra == "nlp"
Requires-Dist: omegaconf<=2.3; extra == "nlp"
Requires-Dist: peft; extra == "nlp"
Requires-Dist: torchmetrics>=0.11.0; extra == "nlp"
Requires-Dist: transformers; extra == "nlp"
Requires-Dist: wandb; extra == "nlp"
Requires-Dist: webdataset>=0.2.86; extra == "nlp"
Requires-Dist: nv_one_logger_core>=2.3.1; extra == "nlp"
Requires-Dist: nv_one_logger_training_telemetry>=2.3.1; extra == "nlp"
Requires-Dist: nv_one_logger_pytorch_lightning_integration>=2.3.1; extra == "nlp"
Provides-Extra: llm
Requires-Dist: accelerated-scan; extra == "llm"
Requires-Dist: boto3; extra == "llm"
Requires-Dist: faiss-cpu; extra == "llm"
Requires-Dist: flask_restful; extra == "llm"
Requires-Dist: ftfy; extra == "llm"
Requires-Dist: gdown; extra == "llm"
Requires-Dist: h5py; extra == "llm"
Requires-Dist: ijson; extra == "llm"
Requires-Dist: jieba; extra == "llm"
Requires-Dist: markdown2; extra == "llm"
Requires-Dist: matplotlib>=3.3.2; extra == "llm"
Requires-Dist: megatron_core; extra == "llm"
Requires-Dist: multi-storage-client>=0.21.0; extra == "llm"
Requires-Dist: nltk>=3.6.5; extra == "llm"
Requires-Dist: numpy<2; extra == "llm"
Requires-Dist: nvidia-modelopt==0.37.0; extra == "llm"
Requires-Dist: nvidia-resiliency-ext<1.0.0,>=0.3.0; platform_system != "Darwin" and extra == "llm"
Requires-Dist: nvtx; extra == "llm"
Requires-Dist: opencc; extra == "llm"
Requires-Dist: pangu; extra == "llm"
Requires-Dist: prettytable; extra == "llm"
Requires-Dist: rapidfuzz; extra == "llm"
Requires-Dist: rouge_score; extra == "llm"
Requires-Dist: sacrebleu; extra == "llm"
Requires-Dist: sentence_transformers; extra == "llm"
Requires-Dist: tensorstore<0.1.72; platform_system != "Darwin" and extra == "llm"
Requires-Dist: tiktoken==0.7.0; extra == "llm"
Requires-Dist: zarr<3.0.0,>=2.18.2; extra == "llm"
Requires-Dist: datasets; extra == "llm"
Requires-Dist: einops; extra == "llm"
Requires-Dist: inflect; extra == "llm"
Requires-Dist: mediapy==1.1.6; extra == "llm"
Requires-Dist: pandas; extra == "llm"
Requires-Dist: sacremoses>=0.0.43; extra == "llm"
Requires-Dist: sentencepiece<1.0.0; extra == "llm"
Requires-Dist: cloudpickle; extra == "llm"
Requires-Dist: fiddle; extra == "llm"
Requires-Dist: hydra-core<=1.3.2,>1.3; extra == "llm"
Requires-Dist: lightning<=2.4.0,>2.2.1; extra == "llm"
Requires-Dist: omegaconf<=2.3; extra == "llm"
Requires-Dist: peft; extra == "llm"
Requires-Dist: torchmetrics>=0.11.0; extra == "llm"
Requires-Dist: transformers; extra == "llm"
Requires-Dist: wandb; extra == "llm"
Requires-Dist: webdataset>=0.2.86; extra == "llm"
Requires-Dist: nv_one_logger_core>=2.3.1; extra == "llm"
Requires-Dist: nv_one_logger_training_telemetry>=2.3.1; extra == "llm"
Requires-Dist: nv_one_logger_pytorch_lightning_integration>=2.3.1; extra == "llm"
Provides-Extra: multimodal
Requires-Dist: addict; extra == "multimodal"
Requires-Dist: clip; extra == "multimodal"
Requires-Dist: decord; (sys_platform == "linux" and platform_machine == "x86_64") and extra == "multimodal"
Requires-Dist: diffusers>=0.19.3; extra == "multimodal"
Requires-Dist: einops_exts; extra == "multimodal"
Requires-Dist: imageio; extra == "multimodal"
Requires-Dist: kornia; extra == "multimodal"
Requires-Dist: megatron-energon==5.2.0; extra == "multimodal"
Requires-Dist: nerfacc>=0.5.3; extra == "multimodal"
Requires-Dist: open_clip_torch==2.24.0; extra == "multimodal"
Requires-Dist: qwen_vl_utils; extra == "multimodal"
Requires-Dist: taming-transformers; extra == "multimodal"
Requires-Dist: torchdiffeq; extra == "multimodal"
Requires-Dist: torchsde; extra == "multimodal"
Requires-Dist: trimesh; extra == "multimodal"
Requires-Dist: accelerated-scan; extra == "multimodal"
Requires-Dist: boto3; extra == "multimodal"
Requires-Dist: faiss-cpu; extra == "multimodal"
Requires-Dist: flask_restful; extra == "multimodal"
Requires-Dist: ftfy; extra == "multimodal"
Requires-Dist: gdown; extra == "multimodal"
Requires-Dist: h5py; extra == "multimodal"
Requires-Dist: ijson; extra == "multimodal"
Requires-Dist: jieba; extra == "multimodal"
Requires-Dist: markdown2; extra == "multimodal"
Requires-Dist: matplotlib>=3.3.2; extra == "multimodal"
Requires-Dist: megatron_core; extra == "multimodal"
Requires-Dist: multi-storage-client>=0.21.0; extra == "multimodal"
Requires-Dist: nltk>=3.6.5; extra == "multimodal"
Requires-Dist: numpy<2; extra == "multimodal"
Requires-Dist: nvidia-modelopt==0.37.0; extra == "multimodal"
Requires-Dist: nvidia-resiliency-ext<1.0.0,>=0.3.0; platform_system != "Darwin" and extra == "multimodal"
Requires-Dist: nvtx; extra == "multimodal"
Requires-Dist: opencc; extra == "multimodal"
Requires-Dist: pangu; extra == "multimodal"
Requires-Dist: prettytable; extra == "multimodal"
Requires-Dist: rapidfuzz; extra == "multimodal"
Requires-Dist: rouge_score; extra == "multimodal"
Requires-Dist: sacrebleu; extra == "multimodal"
Requires-Dist: sentence_transformers; extra == "multimodal"
Requires-Dist: tensorstore<0.1.72; platform_system != "Darwin" and extra == "multimodal"
Requires-Dist: tiktoken==0.7.0; extra == "multimodal"
Requires-Dist: zarr<3.0.0,>=2.18.2; extra == "multimodal"
Requires-Dist: datasets; extra == "multimodal"
Requires-Dist: einops; extra == "multimodal"
Requires-Dist: inflect; extra == "multimodal"
Requires-Dist: mediapy==1.1.6; extra == "multimodal"
Requires-Dist: pandas; extra == "multimodal"
Requires-Dist: sacremoses>=0.0.43; extra == "multimodal"
Requires-Dist: sentencepiece<1.0.0; extra == "multimodal"
Requires-Dist: cloudpickle; extra == "multimodal"
Requires-Dist: fiddle; extra == "multimodal"
Requires-Dist: hydra-core<=1.3.2,>1.3; extra == "multimodal"
Requires-Dist: lightning<=2.4.0,>2.2.1; extra == "multimodal"
Requires-Dist: omegaconf<=2.3; extra == "multimodal"
Requires-Dist: peft; extra == "multimodal"
Requires-Dist: torchmetrics>=0.11.0; extra == "multimodal"
Requires-Dist: transformers; extra == "multimodal"
Requires-Dist: wandb; extra == "multimodal"
Requires-Dist: webdataset>=0.2.86; extra == "multimodal"
Requires-Dist: nv_one_logger_core>=2.3.1; extra == "multimodal"
Requires-Dist: nv_one_logger_training_telemetry>=2.3.1; extra == "multimodal"
Requires-Dist: nv_one_logger_pytorch_lightning_integration>=2.3.1; extra == "multimodal"
Requires-Dist: datasets; extra == "multimodal"
Requires-Dist: einops; extra == "multimodal"
Requires-Dist: inflect; extra == "multimodal"
Requires-Dist: mediapy==1.1.6; extra == "multimodal"
Requires-Dist: pandas; extra == "multimodal"
Requires-Dist: sacremoses>=0.0.43; extra == "multimodal"
Requires-Dist: sentencepiece<1.0.0; extra == "multimodal"
Requires-Dist: cloudpickle; extra == "multimodal"
Requires-Dist: fiddle; extra == "multimodal"
Requires-Dist: hydra-core<=1.3.2,>1.3; extra == "multimodal"
Requires-Dist: lightning<=2.4.0,>2.2.1; extra == "multimodal"
Requires-Dist: omegaconf<=2.3; extra == "multimodal"
Requires-Dist: peft; extra == "multimodal"
Requires-Dist: torchmetrics>=0.11.0; extra == "multimodal"
Requires-Dist: transformers; extra == "multimodal"
Requires-Dist: wandb; extra == "multimodal"
Requires-Dist: webdataset>=0.2.86; extra == "multimodal"
Requires-Dist: nv_one_logger_core>=2.3.1; extra == "multimodal"
Requires-Dist: nv_one_logger_training_telemetry>=2.3.1; extra == "multimodal"
Requires-Dist: nv_one_logger_pytorch_lightning_integration>=2.3.1; extra == "multimodal"
Dynamic: author
Dynamic: download-url
Dynamic: home-page
Dynamic: license-file
Dynamic: maintainer
Dynamic: provides-extra
Dynamic: requires-dist
Dynamic: requires-python
